{"lastUsed":1695189003245,"path":"C:\/jsk\/jsp_workspace","projectCount":4,"recentFiles":[{"path":"\/Hello\/src\/main\/java\/sevlet","parentWorkspace":"C:\/jsk\/jsp_workspace","name":"CurrentTime.java","lastModified":1695093240905,"locationURI":"file:\/C:\/jsk\/jsp_workspace\/Hello\/src\/main\/java\/sevlet\/CurrentTime.java"},{"path":"\/Hello\/src\/main\/webapp","parentWorkspace":"C:\/jsk\/jsp_workspace","name":"LoginSuccess.jsp","lastModified":1695094837487,"locationURI":"file:\/C:\/jsk\/jsp_workspace\/Hello\/src\/main\/webapp\/LoginSuccess.jsp"},{"path":"\/BankProj\/src\/main\/webapp","parentWorkspace":"C:\/jsk\/jsp_workspace","name":"header.jsp","lastModified":1695176660020,"locationURI":"file:\/C:\/jsk\/jsp_workspace\/BankProj\/src\/main\/webapp\/header.jsp"},{"path":"\/Servers\/Tomcat v9.0 Server at localhost-config","parentWorkspace":"C:\/jsk\/jsp_workspace","name":"server.xml","lastModified":1695105260299,"locationURI":"file:\/C:\/jsk\/jsp_workspace\/Servers\/Tomcat%20v9.0%20Server%20at%20localhost-config\/server.xml"},{"path":"\/JspExam5\/src\/main\/webapp","parentWorkspace":"C:\/jsk\/jsp_workspace","name":"requestTest1.jsp","lastModified":1695187129683,"locationURI":"file:\/C:\/jsk\/jsp_workspace\/JspExam5\/src\/main\/webapp\/requestTest1.jsp"},{"path":"\/Hello\/src\/main\/webapp","parentWorkspace":"C:\/jsk\/jsp_workspace","name":"memRegSuccess.jsp","lastModified":1695103647671,"locationURI":"file:\/C:\/jsk\/jsp_workspace\/Hello\/src\/main\/webapp\/memRegSuccess.jsp"},{"path":"\/Hello\/src\/main\/webapp","parentWorkspace":"C:\/jsk\/jsp_workspace","name":"CurrentTime.jsp","lastModified":1695104328612,"locationURI":"file:\/C:\/jsk\/jsp_workspace\/Hello\/src\/main\/webapp\/CurrentTime.jsp"},{"path":"\/BankProj\/src\/main\/java\/servlet","parentWorkspace":"C:\/jsk\/jsp_workspace","name":"Main.java","lastModified":1695172765799,"locationURI":"file:\/C:\/jsk\/jsp_workspace\/BankProj\/src\/main\/java\/servlet\/Main.java"},{"path":"\/BankProj\/src\/main\/webapp","parentWorkspace":"C:\/jsk\/jsp_workspace","name":"deposit.jsp","lastModified":1695177193948,"locationURI":"file:\/C:\/jsk\/jsp_workspace\/BankProj\/src\/main\/webapp\/deposit.jsp"},{"path":"\/JspExam\/src\/main\/webapp","parentWorkspace":"C:\/jsk\/jsp_workspace","name":"includeTest.jsp","lastModified":1695105336545,"locationURI":"file:\/C:\/jsk\/jsp_workspace\/JspExam\/src\/main\/webapp\/includeTest.jsp"},{"path":"\/JspExam5\/src\/main\/webapp","parentWorkspace":"C:\/jsk\/jsp_workspace","name":"requestTest1_From.jsp","lastModified":1695188520493,"locationURI":"file:\/C:\/jsk\/jsp_workspace\/JspExam5\/src\/main\/webapp\/requestTest1_From.jsp"},{"path":"\/BankProj\/src\/main\/webapp","parentWorkspace":"C:\/jsk\/jsp_workspace","name":"allaccountinfo.jsp","lastModified":1695177437750,"locationURI":"file:\/C:\/jsk\/jsp_workspace\/BankProj\/src\/main\/webapp\/allaccountinfo.jsp"},{"path":"\/Hello\/src\/main\/java\/sevlet","parentWorkspace":"C:\/jsk\/jsp_workspace","name":"LoginProcess.java","lastModified":1695095142148,"locationURI":"file:\/C:\/jsk\/jsp_workspace\/Hello\/src\/main\/java\/sevlet\/LoginProcess.java"},{"path":"\/BankProj\/src\/main\/webapp","parentWorkspace":"C:\/jsk\/jsp_workspace","name":"makeaccount.jsp","lastModified":1695179442048,"locationURI":"file:\/C:\/jsk\/jsp_workspace\/BankProj\/src\/main\/webapp\/makeaccount.jsp"},{"path":"\/BankProj\/src\/main\/webapp","parentWorkspace":"C:\/jsk\/jsp_workspace","name":"accountinfo.jsp","lastModified":1695176883571,"locationURI":"file:\/C:\/jsk\/jsp_workspace\/BankProj\/src\/main\/webapp\/accountinfo.jsp"},{"path":"\/JspExam\/src\/main\/webapp","parentWorkspace":"C:\/jsk\/jsp_workspace","name":"header.jsp","lastModified":1695104951296,"locationURI":"file:\/C:\/jsk\/jsp_workspace\/JspExam\/src\/main\/webapp\/header.jsp"},{"path":"\/JspExam\/src\/main\/webapp","parentWorkspace":"C:\/jsk\/jsp_workspace","name":"footer.jsp","lastModified":1695104995933,"locationURI":"file:\/C:\/jsk\/jsp_workspace\/JspExam\/src\/main\/webapp\/footer.jsp"},{"path":"\/Hello\/src\/main\/webapp","parentWorkspace":"C:\/jsk\/jsp_workspace","name":"hello.html","lastModified":1695104049078,"locationURI":"file:\/C:\/jsk\/jsp_workspace\/Hello\/src\/main\/webapp\/hello.html"},{"path":"\/Hello\/src\/main\/java\/sevlet","parentWorkspace":"C:\/jsk\/jsp_workspace","name":"MemRegProcess.java","lastModified":1695103678031,"locationURI":"file:\/C:\/jsk\/jsp_workspace\/Hello\/src\/main\/java\/sevlet\/MemRegProcess.java"},{"path":"\/BankProj\/src\/main\/webapp","parentWorkspace":"C:\/jsk\/jsp_workspace","name":"main.jsp","lastModified":1695176683852,"locationURI":"file:\/C:\/jsk\/jsp_workspace\/BankProj\/src\/main\/webapp\/main.jsp"},{"path":"\/BankProj\/src\/main\/webapp","parentWorkspace":"C:\/jsk\/jsp_workspace","name":"accountinfoform.jsp","lastModified":1695177251864,"locationURI":"file:\/C:\/jsk\/jsp_workspace\/BankProj\/src\/main\/webapp\/accountinfoform.jsp"},{"path":"\/JspExam\/src\/main\/webapp","parentWorkspace":"C:\/jsk\/jsp_workspace","name":"jspScriptTest.jsp","lastModified":1695170286678,"locationURI":"file:\/C:\/jsk\/jsp_workspace\/JspExam\/src\/main\/webapp\/jspScriptTest.jsp"},{"path":"\/Hello\/src\/main\/webapp","parentWorkspace":"C:\/jsk\/jsp_workspace","name":"memReg.html","lastModified":1695103514717,"locationURI":"file:\/C:\/jsk\/jsp_workspace\/Hello\/src\/main\/webapp\/memReg.html"},{"path":"\/BankProj\/src\/main\/webapp","parentWorkspace":"C:\/jsk\/jsp_workspace","name":"withdraw.jsp","lastModified":1695177125665,"locationURI":"file:\/C:\/jsk\/jsp_workspace\/BankProj\/src\/main\/webapp\/withdraw.jsp"},{"path":"\/Hello\/src\/main\/webapp","parentWorkspace":"C:\/jsk\/jsp_workspace","name":"login.jsp","lastModified":1695095007332,"locationURI":"file:\/C:\/jsk\/jsp_workspace\/Hello\/src\/main\/webapp\/login.jsp"},{"path":"\/JspExam5\/src\/main\/webapp","parentWorkspace":"C:\/jsk\/jsp_workspace","name":"requestTest2.jsp","lastModified":1695188597950,"locationURI":"file:\/C:\/jsk\/jsp_workspace\/JspExam5\/src\/main\/webapp\/requestTest2.jsp"}]}